{"nodes": [{"id": "92526f8c-52dc-4c53-82da-928b865db248", "type": "text"}, {"id": "b819fab5-8f70-4fdb-bed1-0f660789de9f", "type": "text"}, {"id": "7c057ea4-a83b-4b8c-8c0f-a6540fc219bd", "type": "image"}, {"id": "9fadd690-8d7a-4cd2-9af4-b0576c839bc5", "type": "video"}, {"id": "577840c4-f8bd-400f-8e78-3b4f39d33cdc", "type": "countdown"}, {"id": "7f18eb29-ef0c-4cfe-bde1-df246ae02a51", "type": "button"}, {"id": "41e05301-c5a3-4b15-a206-728c5ac81760", "type": "form"}], "nodeData": [{"type": "text", "content": "<p>Edit Your Text Content Here.</p><p></p>", "styles": {"desktop": {"display": true, "opacity": 1, "background": {"color": "transparent", "type": "Solid Color", "gradient": {"type": "Linear", "color1": "#fc4a1a", "color2": "#f7b733", "angle": 45}, "image": {"url": "/assets/images/default-vnode.png", "overlayColor": "transparent", "overlayOpacity": 0.5, "size": "Auto", "position": "Center"}}, "dimensions": {"width": {"type": "px", "value": 230}, "height": 36}, "alignments": {"vertical": "Start", "horizontal": "Start"}, "font": {"family": "Josefin Sans", "size": 36, "alignment": "Left", "color": "", "lineHeight": 0, "letterSpacing": 0, "weight": 300}, "linked": {}, "position": {"top": 94.40625, "left": 153}, "borderRadius": {"value": 0, "type": "px"}, "border": {"type": "None", "color": "#aa0eb3", "size": 1}, "zIndex": 10, "frontValues": {"width": 15.13967169951043, "left": 10.07117291315259, "height": 0}}, "mobile": {"display": true, "opacity": 1, "background": {"color": "transparent", "type": "Solid Color", "gradient": {"type": "Linear", "color1": "#fc4a1a", "color2": "#f7b733", "angle": 45}, "image": {"url": "/assets/images/default-vnode.png", "overlayColor": "transparent", "overlayOpacity": 0.5, "size": "Auto", "position": "Center"}}, "dimensions": {"width": {"type": "px", "value": 230}, "height": 72}, "alignments": {"vertical": "Start", "horizontal": "Start"}, "font": {"family": "Josefin Sans", "size": 36, "alignment": "Left", "color": "", "lineHeight": 0, "letterSpacing": 0, "weight": 300}, "linked": {}, "position": {"top": 95.40625, "left": 138}, "borderRadius": {"value": 0, "type": "px"}, "border": {"type": "None", "color": "#aa0eb3", "size": 1}, "zIndex": 10, "frontValues": {"width": 62.5, "left": 37.5, "height": 0}}, "tablet": {"display": true, "opacity": 1, "background": {"color": "transparent", "type": "Solid Color", "gradient": {"type": "Linear", "color1": "#fc4a1a", "color2": "#f7b733", "angle": 45}, "image": {"url": "/assets/images/default-vnode.png", "overlayColor": "transparent", "overlayOpacity": 0.5, "size": "Auto", "position": "Center"}}, "dimensions": {"width": {"type": "px", "value": 230}, "height": 180}, "alignments": {"vertical": "Start", "horizontal": "Start"}, "font": {"family": "Josefin Sans", "size": 36, "alignment": "Left", "color": "", "lineHeight": 0, "letterSpacing": 0, "weight": 300}, "linked": {}, "position": {"top": 94.40625, "left": 153}, "borderRadius": {"value": 0, "type": "px"}, "border": {"type": "None", "color": "#aa0eb3", "size": 1}, "zIndex": 10, "frontValues": {"width": 29.947916666666668, "left": 19.921875, "height": 0}}}}, {"type": "text", "content": "<p>Edit Your Text Content Here.</p><p></p>", "styles": {"desktop": {"display": true, "opacity": 1, "background": {"color": "transparent", "type": "Solid Color", "gradient": {"type": "Linear", "color1": "#fc4a1a", "color2": "#f7b733", "angle": 45}, "image": {"url": "/assets/images/default-vnode.png", "overlayColor": "transparent", "overlayOpacity": 0.5, "size": "Auto", "position": "Center"}}, "dimensions": {"width": {"type": "px", "value": 230}, "height": 36}, "alignments": {"vertical": "Start", "horizontal": "Start"}, "font": {"family": "Josefin Sans", "size": 36, "alignment": "Left", "color": "", "lineHeight": 0, "letterSpacing": 0, "weight": 300}, "linked": {}, "position": {"top": 108.40625, "left": 562}, "borderRadius": {"value": 0, "type": "px"}, "border": {"type": "None", "color": "#aa0eb3", "size": 1}, "zIndex": 10, "frontValues": {"width": 15.13967169951043, "left": 36.99345867445592, "height": 0}}, "mobile": {"display": true, "opacity": 1, "background": {"color": "transparent", "type": "Solid Color", "gradient": {"type": "Linear", "color1": "#fc4a1a", "color2": "#f7b733", "angle": 45}, "image": {"url": "/assets/images/default-vnode.png", "overlayColor": "transparent", "overlayOpacity": 0.5, "size": "Auto", "position": "Center"}}, "dimensions": {"width": {"type": "px", "value": 230}, "height": 72}, "alignments": {"vertical": "Start", "horizontal": "Start"}, "font": {"family": "Josefin Sans", "size": 36, "alignment": "Left", "color": "", "lineHeight": 0, "letterSpacing": 0, "weight": 300}, "linked": {}, "position": {"top": 104.40625, "left": 138}, "borderRadius": {"value": 0, "type": "px"}, "border": {"type": "None", "color": "#aa0eb3", "size": 1}, "zIndex": 10, "frontValues": {"width": 62.5, "left": 37.5, "height": 0}}, "tablet": {"display": true, "opacity": 1, "background": {"color": "transparent", "type": "Solid Color", "gradient": {"type": "Linear", "color1": "#fc4a1a", "color2": "#f7b733", "angle": 45}, "image": {"url": "/assets/images/default-vnode.png", "overlayColor": "transparent", "overlayOpacity": 0.5, "size": "Auto", "position": "Center"}}, "dimensions": {"width": {"type": "px", "value": 230}, "height": 180}, "alignments": {"vertical": "Start", "horizontal": "Start"}, "font": {"family": "Josefin Sans", "size": 36, "alignment": "Left", "color": "", "lineHeight": 0, "letterSpacing": 0, "weight": 300}, "linked": {}, "position": {"top": 108.40625, "left": 538}, "borderRadius": {"value": 0, "type": "px"}, "border": {"type": "None", "color": "#aa0eb3", "size": 1}, "zIndex": 10, "frontValues": {"width": 29.947916666666668, "left": 70.05208333333334, "height": 0}}}}, {"type": "image", "content": "/assets/local/images/default-vnode.png", "styles": {"desktop": {"display": true, "opacity": 1, "background": {"color": "transparent", "type": "Solid Color", "gradient": {"type": "Linear", "color1": "#fc4a1a", "color2": "#f7b733", "angle": 45}, "image": {"url": "/assets/images/default-vnode.png", "overlayColor": "transparent", "overlayOpacity": 0.5, "size": "Auto", "position": "Center"}}, "dimensions": {"width": {"type": "px", "value": 300}, "height": {"type": "px", "value": 300}}, "alignments": {"vertical": "Start", "horizontal": "Start"}, "font": {"family": "Josefin Sans", "size": 36, "alignment": "Left", "color": "", "lineHeight": 0, "letterSpacing": 0, "weight": 300}, "linked": {}, "position": {"top": 179.40625, "left": 966}, "borderRadius": {"value": 0, "type": "px"}, "border": {"type": "None", "color": "#aa0eb3", "size": 1}, "zIndex": 10, "frontValues": {"width": 19.747397868926647, "left": 63.5866211379438, "height": 0}}, "mobile": {"display": true, "opacity": 1, "background": {"color": "transparent", "type": "Solid Color", "gradient": {"type": "Linear", "color1": "#fc4a1a", "color2": "#f7b733", "angle": 45}, "image": {"url": "/assets/images/default-vnode.png", "overlayColor": "transparent", "overlayOpacity": 0.5, "size": "Auto", "position": "Center"}}, "dimensions": {"width": {"type": "px", "value": 295}, "height": {"type": "px", "value": 299}}, "alignments": {"vertical": "Start", "horizontal": "Start"}, "font": {"family": "Josefin Sans", "size": 36, "alignment": "Left", "color": "", "lineHeight": 0, "letterSpacing": 0, "weight": 300}, "linked": {"dimensions": true}, "position": {"top": 179.40625, "left": 0}, "borderRadius": {"value": 0, "type": "px"}, "border": {"type": "None", "color": "#aa0eb3", "size": 1}, "zIndex": 10, "frontValues": {"width": 80.16304347826086, "left": 0, "height": 0}}, "tablet": {"display": true, "opacity": 1, "background": {"color": "transparent", "type": "Solid Color", "gradient": {"type": "Linear", "color1": "#fc4a1a", "color2": "#f7b733", "angle": 45}, "image": {"url": "/assets/images/default-vnode.png", "overlayColor": "transparent", "overlayOpacity": 0.5, "size": "Auto", "position": "Center"}}, "dimensions": {"width": {"type": "px", "value": 300}, "height": {"type": "px", "value": 300}}, "alignments": {"vertical": "Start", "horizontal": "Start"}, "font": {"family": "Josefin Sans", "size": 36, "alignment": "Left", "color": "", "lineHeight": 0, "letterSpacing": 0, "weight": 300}, "linked": {}, "position": {"top": 179.40625, "left": 468}, "borderRadius": {"value": 0, "type": "px"}, "border": {"type": "None", "color": "#aa0eb3", "size": 1}, "zIndex": 10, "frontValues": {"width": 39.0625, "left": 60.9375, "height": 0}}}}, {"type": "video", "content": "/assets/local/videos/default-vnode.mp4", "styles": {"desktop": {"display": true, "opacity": 1, "background": {"color": "transparent", "type": "Solid Color", "gradient": {"type": "Linear", "color1": "#fc4a1a", "color2": "#f7b733", "angle": 45}, "image": {"url": "/assets/images/default-vnode.png", "overlayColor": "transparent", "overlayOpacity": 0.5, "size": "Auto", "position": "Center"}}, "dimensions": {"width": {"type": "px", "value": 500}, "height": 854.546875}, "alignments": {"vertical": "Start", "horizontal": "Start"}, "font": {"family": "Josefin Sans", "size": 36, "alignment": "Left", "color": "", "lineHeight": 0, "letterSpacing": 0, "weight": 300}, "linked": {}, "position": {"top": 165.40625, "left": 0}, "borderRadius": {"value": 0, "type": "px"}, "border": {"type": "None", "color": "#aa0eb3", "size": 1}, "zIndex": 10, "frontValues": {"width": 32.912329781544415, "left": 0, "height": 0}}, "mobile": {"display": true, "opacity": 1, "background": {"color": "transparent", "type": "Solid Color", "gradient": {"type": "Linear", "color1": "#fc4a1a", "color2": "#f7b733", "angle": 45}, "image": {"url": "/assets/images/default-vnode.png", "overlayColor": "transparent", "overlayOpacity": 0.5, "size": "Auto", "position": "Center"}}, "dimensions": {"width": {"value": 368, "type": "px"}, "height": 250}, "alignments": {"vertical": "Start", "horizontal": "Start"}, "font": {"family": "Josefin Sans", "size": 36, "alignment": "Left", "color": "", "lineHeight": 0, "letterSpacing": 0, "weight": 300}, "linked": {}, "position": {"top": 152.40625, "left": 0}, "borderRadius": {"value": 0, "type": "px"}, "border": {"type": "None", "color": "#aa0eb3", "size": 1}, "zIndex": 10, "frontValues": {"width": 100, "left": 0, "height": 0}}, "tablet": {"display": true, "opacity": 1, "background": {"color": "transparent", "type": "Solid Color", "gradient": {"type": "Linear", "color1": "#fc4a1a", "color2": "#f7b733", "angle": 45}, "image": {"url": "/assets/images/default-vnode.png", "overlayColor": "transparent", "overlayOpacity": 0.5, "size": "Auto", "position": "Center"}}, "dimensions": {"width": {"type": "px", "value": 500}, "height": 142.171875}, "alignments": {"vertical": "Start", "horizontal": "Start"}, "font": {"family": "Josefin Sans", "size": 36, "alignment": "Left", "color": "", "lineHeight": 0, "letterSpacing": 0, "weight": 300}, "linked": {}, "position": {"top": 165.40625, "left": 0}, "borderRadius": {"value": 0, "type": "px"}, "border": {"type": "None", "color": "#aa0eb3", "size": 1}, "zIndex": 10, "frontValues": {"width": 65.10416666666666, "left": 0, "height": 0}}}}, {"type": "countdown", "content": "2023-09-14T08:18:00.699Z", "styles": {"desktop": {"display": true, "opacity": 1, "background": {"color": "transparent", "type": "Solid Color", "gradient": {"type": "Linear", "color1": "#fc4a1a", "color2": "#f7b733", "angle": 45}, "image": {"url": "/assets/images/default-vnode.png", "overlayColor": "transparent", "overlayOpacity": 0.5, "size": "Auto", "position": "Center"}}, "dimensions": {"width": {"type": "px", "value": 418}, "height": {"type": "px", "value": 76}}, "alignments": {"vertical": "Start", "horizontal": "Start"}, "font": {"family": "Josefin Sans", "size": 36, "alignment": "Left", "color": "", "lineHeight": 0, "letterSpacing": 0, "weight": 300}, "linked": {}, "position": {"top": 200.40625, "left": 724}, "borderRadius": {"value": 0, "type": "px"}, "border": {"type": "None", "color": "#aa0eb3", "size": 1}, "zIndex": 10, "content": {"fontSize": {"dateTime": 54, "label": 16}, "color": {"dateTime": "none", "label": "none"}, "hSpace": 16, "vSpace": 0}, "frontValues": {"width": 27.514707697371126, "left": 47.65705352367631, "height": 0}}, "mobile": {"display": true, "opacity": 1, "background": {"color": "transparent", "type": "Solid Color", "gradient": {"type": "Linear", "color1": "#fc4a1a", "color2": "#f7b733", "angle": 45}, "image": {"url": "/assets/images/default-vnode.png", "overlayColor": "transparent", "overlayOpacity": 0.5, "size": "Auto", "position": "Center"}}, "dimensions": {"width": {"value": 368, "type": "px"}, "height": {"type": "px", "value": 76}}, "alignments": {"vertical": "Start", "horizontal": "Start"}, "font": {"family": "Josefin Sans", "size": 36, "alignment": "Left", "color": "", "lineHeight": 0, "letterSpacing": 0, "weight": 300}, "linked": {}, "position": {"top": 224.40625, "left": 0}, "borderRadius": {"value": 0, "type": "px"}, "border": {"type": "None", "color": "#aa0eb3", "size": 1}, "zIndex": 10, "content": {"fontSize": {"dateTime": 54, "label": 16}, "color": {"dateTime": "none", "label": "none"}, "hSpace": 16, "vSpace": 0}, "frontValues": {"width": 100, "left": 0, "height": 0}}, "tablet": {"display": true, "opacity": 1, "background": {"color": "transparent", "type": "Solid Color", "gradient": {"type": "Linear", "color1": "#fc4a1a", "color2": "#f7b733", "angle": 45}, "image": {"url": "/assets/images/default-vnode.png", "overlayColor": "transparent", "overlayOpacity": 0.5, "size": "Auto", "position": "Center"}}, "dimensions": {"width": {"type": "px", "value": 418}, "height": {"type": "px", "value": 76}}, "alignments": {"vertical": "Start", "horizontal": "Start"}, "font": {"family": "Josefin Sans", "size": 36, "alignment": "Left", "color": "", "lineHeight": 0, "letterSpacing": 0, "weight": 300}, "linked": {}, "position": {"top": 200.40625, "left": 350}, "borderRadius": {"value": 0, "type": "px"}, "border": {"type": "None", "color": "#aa0eb3", "size": 1}, "zIndex": 10, "content": {"fontSize": {"dateTime": 54, "label": 16}, "color": {"dateTime": "none", "label": "none"}, "hSpace": 16, "vSpace": 0}, "frontValues": {"width": 54.427083333333336, "left": 45.57291666666667, "height": 0}}}}, {"type": "button", "content": {"text": "Button Text", "iconPosition": "Left", "link": {"type": "None"}}, "styles": {"desktop": {"display": true, "opacity": 1, "background": {"color": "#aa0eb3", "type": "Solid Color", "gradient": {"type": "Linear", "color1": "#fc4a1a", "color2": "#f7b733", "angle": 45}, "image": {"url": "/assets/images/default-vnode.png", "overlayColor": "transparent", "overlayOpacity": 0.5, "size": "Auto", "position": "Center"}}, "dimensions": {"width": {"type": "px", "value": 172}, "height": {"type": "px", "value": 46}}, "alignments": {"vertical": "Start", "horizontal": "Start"}, "font": {"family": "Josefin Sans", "size": 14, "alignment": "Left", "color": "white", "lineHeight": 0, "letterSpacing": 0, "weight": 300}, "linked": {}, "position": {"top": 17.40625, "left": 952}, "borderRadius": {"value": 0, "type": "px"}, "border": {"type": "None", "color": "#aa0eb3", "size": 1}, "zIndex": 10, "frontValues": {"width": 11.321841444851277, "left": 62.665075904060565, "height": 0}}, "mobile": {"display": true, "opacity": 1, "background": {"color": "#aa0eb3", "type": "Solid Color", "gradient": {"type": "Linear", "color1": "#fc4a1a", "color2": "#f7b733", "angle": 45}, "image": {"url": "/assets/images/default-vnode.png", "overlayColor": "transparent", "overlayOpacity": 0.5, "size": "Auto", "position": "Center"}}, "dimensions": {"width": {"type": "px", "value": 172}, "height": {"type": "px", "value": 46}}, "alignments": {"vertical": "Start", "horizontal": "Start"}, "font": {"family": "Josefin Sans", "size": 14, "alignment": "Left", "color": "white", "lineHeight": 0, "letterSpacing": 0, "weight": 300}, "linked": {}, "position": {"top": 57.40625, "left": 196}, "borderRadius": {"value": 0, "type": "px"}, "border": {"type": "None", "color": "#aa0eb3", "size": 1}, "zIndex": 10, "frontValues": {"width": 46.73913043478261, "left": 53.2608695652174, "height": 0}}, "tablet": {"display": true, "opacity": 1, "background": {"color": "#aa0eb3", "type": "Solid Color", "gradient": {"type": "Linear", "color1": "#fc4a1a", "color2": "#f7b733", "angle": 45}, "image": {"url": "/assets/images/default-vnode.png", "overlayColor": "transparent", "overlayOpacity": 0.5, "size": "Auto", "position": "Center"}}, "dimensions": {"width": {"type": "px", "value": 172}, "height": {"type": "px", "value": 46}}, "alignments": {"vertical": "Start", "horizontal": "Start"}, "font": {"family": "Josefin Sans", "size": 14, "alignment": "Left", "color": "white", "lineHeight": 0, "letterSpacing": 0, "weight": 300}, "linked": {}, "position": {"top": 17.40625, "left": 596}, "borderRadius": {"value": 0, "type": "px"}, "border": {"type": "None", "color": "#aa0eb3", "size": 1}, "zIndex": 10, "frontValues": {"width": 22.395833333333336, "left": 77.60416666666666, "height": 0}}}}, {"type": "form", "content": {"type": "Normal", "fields": [{"name": "lol", "label": "name", "type": "Text", "style": {"desktop": {"width": 100}}}, {"name": "c9f845e9-ea00-4270-b46e-8a0e7d9d5e28", "label": "", "type": "Text", "style": {"desktop": {"width": 100}}}, {"name": "a59f8274-524d-4b7c-9997-2d4776da052b", "label": "", "type": "Text", "style": {"desktop": {"width": 100}}}], "config": {"method": "POST", "action": "", "spacing": {"fields": 6, "button": 6}, "btn": {"text": "Submit", "position": "Left", "width": "194", "color": "purple", "textColor": "white"}, "fields": {"border": true, "borderColor": "#0000003d", "labelColor": "#607b7c", "inputColor": "#607b7c", "backgroundColor": "transparent", "size": "Big", "style": "Filled"}}}, "styles": {"desktop": {"display": true, "opacity": 1, "background": {"color": "transparent", "type": "Solid Color", "gradient": {"type": "Linear", "color1": "#fc4a1a", "color2": "#f7b733", "angle": 45}, "image": {"url": "/assets/images/default-vnode.png", "overlayColor": "transparent", "overlayOpacity": 0.5, "size": "Auto", "position": "Center"}}, "dimensions": {"width": {"type": "px", "value": 462}, "height": {"type": "px", "value": 446}}, "alignments": {"vertical": "Start", "horizontal": "Start"}, "font": {"family": "Josefin Sans", "size": 36, "alignment": "Left", "color": "", "lineHeight": 0, "letterSpacing": 0, "weight": 300}, "linked": {}, "position": {"top": 113.40625, "left": 767}, "borderRadius": {"value": 0, "type": "px"}, "border": {"type": "None", "color": "#aa0eb3", "size": 1}, "zIndex": 10, "frontValues": {"width": 30.410992718147035, "left": 50.487513884889125, "height": 0}}, "mobile": {"display": true, "opacity": 1, "background": {"color": "transparent", "type": "Solid Color", "gradient": {"type": "Linear", "color1": "#fc4a1a", "color2": "#f7b733", "angle": 45}, "image": {"url": "/assets/images/default-vnode.png", "overlayColor": "transparent", "overlayOpacity": 0.5, "size": "Auto", "position": "Center"}}, "dimensions": {"width": {"value": 368, "type": "px"}, "height": {"type": "px", "value": 446}}, "alignments": {"vertical": "Start", "horizontal": "Start"}, "font": {"family": "Josefin Sans", "size": 36, "alignment": "Left", "color": "", "lineHeight": 0, "letterSpacing": 0, "weight": 300}, "linked": {}, "position": {"top": 113.40625, "left": 0}, "borderRadius": {"value": 0, "type": "px"}, "border": {"type": "None", "color": "#aa0eb3", "size": 1}, "zIndex": 10, "frontValues": {"width": 100, "left": 0, "height": 0}}, "tablet": {"display": true, "opacity": 1, "background": {"color": "transparent", "type": "Solid Color", "gradient": {"type": "Linear", "color1": "#fc4a1a", "color2": "#f7b733", "angle": 45}, "image": {"url": "/assets/images/default-vnode.png", "overlayColor": "transparent", "overlayOpacity": 0.5, "size": "Auto", "position": "Center"}}, "dimensions": {"width": {"type": "px", "value": 462}, "height": {"type": "px", "value": 446}}, "alignments": {"vertical": "Start", "horizontal": "Start"}, "font": {"family": "Josefin Sans", "size": 36, "alignment": "Left", "color": "", "lineHeight": 0, "letterSpacing": 0, "weight": 300}, "linked": {}, "position": {"top": 113.40625, "left": 306}, "borderRadius": {"value": 0, "type": "px"}, "border": {"type": "None", "color": "#aa0eb3", "size": 1}, "zIndex": 10, "frontValues": {"width": 60.15625, "left": 39.84375, "height": 0}}}}], "height": {"desktop": 583.40625, "tablet": 583.40625, "mobile": 583.40625}}